mcfly/__init__.py
mcfly/_version.py
mcfly/find_architecture.py
mcfly/keras_dataset.py
mcfly/modelgen.py
mcfly/task.py
mcfly/models/__init__.py
mcfly/models/base_hyperparameter_generator.py
mcfly/models/cnn.py
mcfly/models/deep_conv_lstm.py
mcfly/models/inception_time.py
mcfly/models/resnet.py
mcfly-4.1.0.dist-info/licenses/LICENSE
mcfly-4.1.0.dist-info/METADATA
mcfly-4.1.0.dist-info/WHEEL
mcfly-4.1.0.dist-info/top_level.txt
mcfly-4.1.0.dist-info/RECORD
