Metadata-Version: 2.4
Name: mcfly
Version: 4.1.0
Summary: Deep learning for time series data
License:                                  Apache License
Project-URL: Homepage, https://github.com/NLeSC/mcfly
Project-URL: Bug Tracker, https://github.com/NLeSC/mcfly/issues
Project-URL: Source, https://github.com/NLeSC/mcfly
Keywords: deep-learning,time-series,auto-ml
Classifier: License :: OSI Approved :: Apache Software License
Classifier: Programming Language :: Python :: 3
Classifier: Programming Language :: Python :: 3.10
Classifier: Programming Language :: Python :: 3.11
Classifier: Programming Language :: Python :: 3.12
Classifier: Programming Language :: Python :: 3 :: Only
Requires-Python: >=3.10
License-File: LICENSE
Requires-Dist: numpy
Requires-Dist: scikit-learn
Requires-Dist: scipy
Requires-Dist: keras>=3.0
Provides-Extra: dev
Requires-Dist: coverage; extra == "dev"
Requires-Dist: prospector[with_pyroma]; extra == "dev"
Requires-Dist: pytest; extra == "dev"
Requires-Dist: pytest-cov; extra == "dev"
Provides-Extra: publishing
Requires-Dist: build; extra == "publishing"
Requires-Dist: twine; extra == "publishing"
Requires-Dist: wheel; extra == "publishing"
Requires-Dist: sphinx; extra == "publishing"
Requires-Dist: sphinx-rtd-theme; extra == "publishing"
Provides-Extra: tensorflow
Requires-Dist: tensorflow>=2.16.1; extra == "tensorflow"
Provides-Extra: torch
Requires-Dist: torch>=2.1.0; extra == "torch"
Provides-Extra: jax
Requires-Dist: jax>=0.4.20; extra == "jax"
Provides-Extra: all
Requires-Dist: mcfly[dev,jax,publishing,tensorflow,torch]; extra == "all"
Dynamic: license-file
